pysysmetrics/__init__.py
pysysmetrics/cli/__init__.py
pysysmetrics/cli/main.py
pysysmetrics/core/__init__.py
pysysmetrics/core/cpu.py
pysysmetrics/core/gpu.py
pysysmetrics/utils/__init__.py
pysysmetrics/utils/test_cpu.py
pysysmetrics/utils/test_gpu.py
pysysmetrics-0.1.3.dist-info/METADATA
pysysmetrics-0.1.3.dist-info/WHEEL
pysysmetrics-0.1.3.dist-info/entry_points.txt
pysysmetrics-0.1.3.dist-info/top_level.txt
pysysmetrics-0.1.3.dist-info/RECORD
